Cope/__init__.py
Cope/boilerplate.py
Cope/colors.py
Cope/debugging.py
Cope/decorators.py
Cope/gym.py
Cope/imports.py
Cope/meme.py
Cope/misc.py
Cope/named_colors.py
Cope/plotly.py
Cope/streamlit.py
Cope/style.cfg
Cope/sympy.py
Cope/assets/look at this photograph mask.png
Cope/assets/look at this photograph template.png
Cope/experimental/Psuedonym.py
Cope/experimental/__init__.py
Cope/experimental/_config.py
Cope/experimental/constants.py
Cope/experimental/data.py
Cope/experimental/geometry.py
Cope/experimental/imports.py
Cope/experimental/iterables.py
Cope/experimental/linalg.py
Cope/experimental/logging.py
Cope/experimental/misc.py
Cope/experimental/point.py
Cope/experimental/pygame.py
Cope/experimental/style.cfg
Cope/experimental/timing.py
cope-2.5.2.dist-info/METADATA
cope-2.5.2.dist-info/WHEEL
cope-2.5.2.dist-info/licenses/LICENSE
cope-2.5.2.dist-info/RECORD
