Metadata-Version: 2.3
Name: Cope
Version: 2.5.2
Summary: A bunch of generic functions and classes useful in multiple projects
License-File: LICENSE
Requires-Dist: rich
Requires-Dist: varname
Provides-Extra: linalg
Requires-Dist: sympy; extra == 'linalg'
